[{"id": "f1bf4a83-5239-4306-a4ea-bc9310e2a57b", "object_type": 13, "health": 18, "hitbox": {"id": "03a9408d-69ca-42f5-b4d1-d370182840c4", "object_type": 14, "width": 140, "height": 30, "position": [0, 0]}, "collidable": true, "destructible": true},
{"id": "594aaccf-7d4a-49b0-a3a2-c569681106fc", "object_type": 13, "health": 18, "hitbox": {"id": "e43d4793-7c58-4bd3-9824-884d73db7cf9", "object_type": 14, "width": 30, "height": 80, "position": [0, 30]}, "collidable": true, "destructible": true},
{"id": "bc223061-0c01-4fb0-a370-3671366a137d", "object_type": 13, "health": 18, "hitbox": {"id": "9db8cb22-6b2c-4c4f-80d7-7c589d2b78ee", "object_type": 14, "width": 140, "height": 30, "position": [0, 110]}, "collidable": true, "destructible": true}]